README.md
setup.py
neslab/find/__init__.py
neslab/find/distributions.py
neslab/find/model.py
neslab_find.egg-info/PKG-INFO
neslab_find.egg-info/SOURCES.txt
neslab_find.egg-info/dependency_links.txt
neslab_find.egg-info/requires.txt
neslab_find.egg-info/top_level.txt