Metadata-Version: 2.1
Name: neslab-find
Version: 0.0.4
Summary: FIND model
Home-page: https://find.nes-lab.org
Author: Kai Geissdoerfer
Author-email: kai.geissdoerfer@tu-dresden.de
License: MIT
Platform: UNKNOWN
Provides-Extra: examples
